mkdocs_changelog_plugin/__init__.py
mkdocs_changelog_plugin/plugin.py
mkdocs_changelog_plugin/css/timeline.css
mkdocs_changelog_plugin/templates/changelog.html
mkdocs_changelog_plugin-0.1.3.dist-info/LICENSE
mkdocs_changelog_plugin-0.1.3.dist-info/METADATA
mkdocs_changelog_plugin-0.1.3.dist-info/WHEEL
mkdocs_changelog_plugin-0.1.3.dist-info/entry_points.txt
mkdocs_changelog_plugin-0.1.3.dist-info/top_level.txt
mkdocs_changelog_plugin-0.1.3.dist-info/RECORD
